[
  {
    "iteration": 1,
    "system_info": {
      "os": "Windows 11 (10.0.22631)",
      "cpu": "AMD Ryzen 7 7735HS with Radeon Graphics",
      "ram": "14 GB",
      "gpu": "AMD Radeon(TM) 680M",
      "cpu_cores": 8,
      "cpu_threads": 16
    },
    "framework_versions": {
      "tauri": "^2",
      "node": "v20.15.0",
      "npm": "10.8.1",
      "cargo": "1.87.0 (99624be96 2025-05-06)",
      "rust": "1.87.0 (17067e9ac 2025-05-09)"
    },
    "session_start_ms": 1748194332756,
    "steps": [
      {
        "cmd": "cargo clean",
        "cwd": "C:\\bakalaura_darba\\blendio-tauri\\src-tauri",
        "start_ms": 1748194332756,
        "end_ms": 1748194334266,
        "duration_ms": 1510,
        "success": true
      },
      {
        "cmd": "npm install",
        "cwd": "C:\\bakalaura_darba\\blendio-tauri",
        "start_ms": 1748194334724,
        "end_ms": 1748194340548,
        "duration_ms": 5824,
        "success": true
      },
      {
        "cmd": "npm run tauri build -- --debug",
        "cwd": "C:\\bakalaura_darba\\blendio-tauri",
        "start_ms": 1748194340548,
        "end_ms": 1748194469117,
        "duration_ms": 128569,
        "success": true
      }
    ],
    "build_commands_used": [
      "npm run tauri build -- --debug"
    ],
    "msi_size_bytes": 10686464,
    "exe_size_bytes": 35885056
  },
  {
    "iteration": 2,
    "system_info": {
      "os": "Windows 11 (10.0.22631)",
      "cpu": "AMD Ryzen 7 7735HS with Radeon Graphics",
      "ram": "14 GB",
      "gpu": "AMD Radeon(TM) 680M",
      "cpu_cores": 8,
      "cpu_threads": 16
    },
    "framework_versions": {
      "tauri": "^2",
      "node": "v20.15.0",
      "npm": "10.8.1",
      "cargo": "1.87.0 (99624be96 2025-05-06)",
      "rust": "1.87.0 (17067e9ac 2025-05-09)"
    },
    "session_start_ms": 1748194469117,
    "steps": [
      {
        "cmd": "cargo clean",
        "cwd": "C:\\bakalaura_darba\\blendio-tauri\\src-tauri",
        "start_ms": 1748194469117,
        "end_ms": 1748194470597,
        "duration_ms": 1480,
        "success": true
      },
      {
        "cmd": "npm run tauri build -- --debug",
        "cwd": "C:\\bakalaura_darba\\blendio-tauri",
        "start_ms": 1748194470597,
        "end_ms": 1748194599743,
        "duration_ms": 129146,
        "success": true
      }
    ],
    "build_commands_used": [
      "npm run tauri build -- --debug"
    ],
    "msi_size_bytes": 10686464,
    "exe_size_bytes": 35885056
  },
  {
    "iteration": 3,
    "system_info": {
      "os": "Windows 11 (10.0.22631)",
      "cpu": "AMD Ryzen 7 7735HS with Radeon Graphics",
      "ram": "14 GB",
      "gpu": "AMD Radeon(TM) 680M",
      "cpu_cores": 8,
      "cpu_threads": 16
    },
    "framework_versions": {
      "tauri": "^2",
      "node": "v20.15.0",
      "npm": "10.8.1",
      "cargo": "1.87.0 (99624be96 2025-05-06)",
      "rust": "1.87.0 (17067e9ac 2025-05-09)"
    },
    "session_start_ms": 1748194599743,
    "steps": [
      {
        "cmd": "cargo clean",
        "cwd": "C:\\bakalaura_darba\\blendio-tauri\\src-tauri",
        "start_ms": 1748194599743,
        "end_ms": 1748194601254,
        "duration_ms": 1511,
        "success": true
      },
      {
        "cmd": "npm run tauri build -- --debug",
        "cwd": "C:\\bakalaura_darba\\blendio-tauri",
        "start_ms": 1748194601254,
        "end_ms": 1748194729515,
        "duration_ms": 128261,
        "success": true
      }
    ],
    "build_commands_used": [
      "npm run tauri build -- --debug"
    ],
    "msi_size_bytes": 10686464,
    "exe_size_bytes": 35885056
  },
  {
    "iteration": 4,
    "system_info": {
      "os": "Windows 11 (10.0.22631)",
      "cpu": "AMD Ryzen 7 7735HS with Radeon Graphics",
      "ram": "14 GB",
      "gpu": "AMD Radeon(TM) 680M",
      "cpu_cores": 8,
      "cpu_threads": 16
    },
    "framework_versions": {
      "tauri": "^2",
      "node": "v20.15.0",
      "npm": "10.8.1",
      "cargo": "1.87.0 (99624be96 2025-05-06)",
      "rust": "1.87.0 (17067e9ac 2025-05-09)"
    },
    "session_start_ms": 1748194729515,
    "steps": [
      {
        "cmd": "cargo clean",
        "cwd": "C:\\bakalaura_darba\\blendio-tauri\\src-tauri",
        "start_ms": 1748194729515,
        "end_ms": 1748194731008,
        "duration_ms": 1493,
        "success": true
      },
      {
        "cmd": "npm run tauri build -- --debug",
        "cwd": "C:\\bakalaura_darba\\blendio-tauri",
        "start_ms": 1748194731008,
        "end_ms": 1748194859684,
        "duration_ms": 128676,
        "success": true
      }
    ],
    "build_commands_used": [
      "npm run tauri build -- --debug"
    ],
    "msi_size_bytes": 10686464,
    "exe_size_bytes": 35885056
  },
  {
    "iteration": 5,
    "system_info": {
      "os": "Windows 11 (10.0.22631)",
      "cpu": "AMD Ryzen 7 7735HS with Radeon Graphics",
      "ram": "14 GB",
      "gpu": "AMD Radeon(TM) 680M",
      "cpu_cores": 8,
      "cpu_threads": 16
    },
    "framework_versions": {
      "tauri": "^2",
      "node": "v20.15.0",
      "npm": "10.8.1",
      "cargo": "1.87.0 (99624be96 2025-05-06)",
      "rust": "1.87.0 (17067e9ac 2025-05-09)"
    },
    "session_start_ms": 1748194859684,
    "steps": [
      {
        "cmd": "cargo clean",
        "cwd": "C:\\bakalaura_darba\\blendio-tauri\\src-tauri",
        "start_ms": 1748194859684,
        "end_ms": 1748194861403,
        "duration_ms": 1719,
        "success": true
      },
      {
        "cmd": "npm run tauri build -- --debug",
        "cwd": "C:\\bakalaura_darba\\blendio-tauri",
        "start_ms": 1748194861403,
        "end_ms": 1748194991062,
        "duration_ms": 129659,
        "success": true
      }
    ],
    "build_commands_used": [
      "npm run tauri build -- --debug"
    ],
    "msi_size_bytes": 10686464,
    "exe_size_bytes": 35885056
  }
]